{
    "zip": 46124,
    "lat": 39.36914,
    "lng": -85.94551,
    "city": "Edinburgh",
    "state_id": "IN",
    "state_name": "Indiana",
    "zcta": true,
    "parent_zcta": NaN,
    "population": 7638.0,
    "density": 40.1,
    "county_fips": 18145,
    "county_name": "Shelby",
    "county_weights": "{\"18145\": 46.4, \"18005\": 30.44, \"18081\": 23.15}",
    "county_names_all": "Shelby|Bartholomew|Johnson",
    "county_fips_all": "18145|18005|18081",
    "imprecise": false,
    "military": false,
    "timezone": "America/Indiana/Indianapolis"
}