{
    "zip": 46750,
    "lat": 40.87677,
    "lng": -85.49674,
    "city": "Huntington",
    "state_id": "IN",
    "state_name": "Indiana",
    "zcta": true,
    "parent_zcta": NaN,
    "population": 27341.0,
    "density": 52.4,
    "county_fips": 18069,
    "county_name": "Huntington",
    "county_weights": "{\"18069\": 99.59, \"18183\": 0.41}",
    "county_names_all": "Huntington|Whitley",
    "county_fips_all": "18069|18183",
    "imprecise": false,
    "military": false,
    "timezone": "America/Indiana/Indianapolis"
}