{
    "zip": 56048,
    "lat": 44.09478,
    "lng": -93.71589,
    "city": "Janesville",
    "state_id": "MN",
    "state_name": "Minnesota",
    "zcta": true,
    "parent_zcta": NaN,
    "population": 4203.0,
    "density": 13.3,
    "county_fips": 27161,
    "county_name": "Waseca",
    "county_weights": "{\"27161\": 76.34, \"27013\": 23.66}",
    "county_names_all": "Waseca|Blue Earth",
    "county_fips_all": "27161|27013",
    "imprecise": false,
    "military": false,
    "timezone": "America/Chicago"
}