{
    "zip": 70815,
    "lat": 30.45537,
    "lng": -91.06648,
    "city": "Baton Rouge",
    "state_id": "LA",
    "state_name": "Louisiana",
    "zcta": true,
    "parent_zcta": NaN,
    "population": 31924.0,
    "density": 1303.9,
    "county_fips": 22033,
    "county_name": "East Baton Rouge",
    "county_weights": "{\"22033\": 100}",
    "county_names_all": "East Baton Rouge",
    "county_fips_all": "22033",
    "imprecise": false,
    "military": false,
    "timezone": "America/Chicago"
}