{
    "zip": 41722,
    "lat": 37.40441,
    "lng": -83.10329,
    "city": "Bulan",
    "state_id": "KY",
    "state_name": "Kentucky",
    "zcta": true,
    "parent_zcta": NaN,
    "population": 1190.0,
    "density": 11.9,
    "county_fips": 21119,
    "county_name": "Knott",
    "county_weights": "{\"21119\": 79.14, \"21193\": 20.86}",
    "county_names_all": "Knott|Perry",
    "county_fips_all": "21119|21193",
    "imprecise": false,
    "military": false,
    "timezone": "America/New_York"
}