{
    "zip": 42372,
    "lat": 37.40588,
    "lng": -87.2773,
    "city": "Sacramento",
    "state_id": "KY",
    "state_name": "Kentucky",
    "zcta": true,
    "parent_zcta": NaN,
    "population": 1620.0,
    "density": 16.5,
    "county_fips": 21149,
    "county_name": "McLean",
    "county_weights": "{\"21149\": 72.05, \"21177\": 27.95}",
    "county_names_all": "McLean|Muhlenberg",
    "county_fips_all": "21149|21177",
    "imprecise": false,
    "military": false,
    "timezone": "America/Chicago"
}