{
    "zip": 58830,
    "lat": 48.60272,
    "lng": -103.46608,
    "city": "Alamo",
    "state_id": "ND",
    "state_name": "North Dakota",
    "zcta": true,
    "parent_zcta": NaN,
    "population": 91.0,
    "density": 0.1,
    "county_fips": 38105,
    "county_name": "Williams",
    "county_weights": "{\"38105\": 59.81, \"38023\": 40.19}",
    "county_names_all": "Williams|Divide",
    "county_fips_all": "38105|38023",
    "imprecise": false,
    "military": false,
    "timezone": "America/Chicago"
}