{
    "zip": 63130,
    "lat": 38.66491,
    "lng": -90.32495,
    "city": "Saint Louis",
    "state_id": "MO",
    "state_name": "Missouri",
    "zcta": true,
    "parent_zcta": NaN,
    "population": 29074.0,
    "density": 2227.9,
    "county_fips": 29189,
    "county_name": "St. Louis",
    "county_weights": "{\"29189\": 98.06, \"29510\": 1.94}",
    "county_names_all": "St. Louis|St. Louis",
    "county_fips_all": "29189|29510",
    "imprecise": false,
    "military": false,
    "timezone": "America/Chicago"
}