{
    "zip": 86434,
    "lat": 35.65959,
    "lng": -113.58538,
    "city": "Peach Springs",
    "state_id": "AZ",
    "state_name": "Arizona",
    "zcta": true,
    "parent_zcta": NaN,
    "population": 1476.0,
    "density": 0.6,
    "county_fips": 4015,
    "county_name": "Mohave",
    "county_weights": "{\"04015\": 95.14, \"04025\": 3.92, \"04005\": 0.94}",
    "county_names_all": "Mohave|Yavapai|Coconino",
    "county_fips_all": "04015|04025|04005",
    "imprecise": false,
    "military": false,
    "timezone": "America/Phoenix"
}