{
    "zip": 18032,
    "lat": 40.65694,
    "lng": -75.46776,
    "city": "Catasauqua",
    "state_id": "PA",
    "state_name": "Pennsylvania",
    "zcta": true,
    "parent_zcta": NaN,
    "population": 9459.0,
    "density": 1817.4,
    "county_fips": 42077,
    "county_name": "Lehigh",
    "county_weights": "{\"42077\": 64.61, \"42095\": 35.39}",
    "county_names_all": "Lehigh|Northampton",
    "county_fips_all": "42077|42095",
    "imprecise": false,
    "military": false,
    "timezone": "America/New_York"
}