{
    "zip": 24120,
    "lat": 36.71891,
    "lng": -80.41277,
    "city": "Meadows Of Dan",
    "state_id": "VA",
    "state_name": "Virginia",
    "zcta": true,
    "parent_zcta": NaN,
    "population": 1608.0,
    "density": 8.2,
    "county_fips": 51141,
    "county_name": "Patrick",
    "county_weights": "{\"51141\": 74.2, \"51063\": 17.02, \"51035\": 8.78}",
    "county_names_all": "Patrick|Floyd|Carroll",
    "county_fips_all": "51141|51063|51035",
    "imprecise": false,
    "military": false,
    "timezone": "America/New_York"
}