{
    "zip": 24503,
    "lat": 37.45272,
    "lng": -79.24286,
    "city": "Lynchburg",
    "state_id": "VA",
    "state_name": "Virginia",
    "zcta": true,
    "parent_zcta": NaN,
    "population": 19978.0,
    "density": 210.0,
    "county_fips": 51019,
    "county_name": "Bedford",
    "county_weights": "{\"51019\": 65.34, \"51680\": 34.66}",
    "county_names_all": "Bedford|Lynchburg",
    "county_fips_all": "51019|51680",
    "imprecise": false,
    "military": false,
    "timezone": "America/New_York"
}