{
    "zip": 26289,
    "lat": 38.98972,
    "lng": -79.51268,
    "city": "Red Creek",
    "state_id": "WV",
    "state_name": "West Virginia",
    "zcta": true,
    "parent_zcta": NaN,
    "population": 13.0,
    "density": 1.3,
    "county_fips": 54093,
    "county_name": "Tucker",
    "county_weights": "{\"54093\": 99.7, \"54083\": 0.3}",
    "county_names_all": "Tucker|Randolph",
    "county_fips_all": "54093|54083",
    "imprecise": false,
    "military": false,
    "timezone": "America/New_York"
}