{
    "zip": 27326,
    "lat": 36.45542,
    "lng": -79.55867,
    "city": "Ruffin",
    "state_id": "NC",
    "state_name": "North Carolina",
    "zcta": true,
    "parent_zcta": NaN,
    "population": 3387.0,
    "density": 20.1,
    "county_fips": 37157,
    "county_name": "Rockingham",
    "county_weights": "{\"37157\": 68.8, \"37033\": 31.2}",
    "county_names_all": "Rockingham|Caswell",
    "county_fips_all": "37157|37033",
    "imprecise": false,
    "military": false,
    "timezone": "America/New_York"
}