{
    "zip": 30292,
    "lat": 33.17207,
    "lng": -84.39438,
    "city": "Williamson",
    "state_id": "GA",
    "state_name": "Georgia",
    "zcta": true,
    "parent_zcta": NaN,
    "population": 6092.0,
    "density": 40.6,
    "county_fips": 13231,
    "county_name": "Pike",
    "county_weights": "{\"13231\": 77.66, \"13255\": 22.34}",
    "county_names_all": "Pike|Spalding",
    "county_fips_all": "13231|13255",
    "imprecise": false,
    "military": false,
    "timezone": "America/New_York"
}