{
    "zip": 30564,
    "lat": 34.47251,
    "lng": -83.8826,
    "city": "Murrayville",
    "state_id": "GA",
    "state_name": "Georgia",
    "zcta": true,
    "parent_zcta": NaN,
    "population": 4815.0,
    "density": 58.3,
    "county_fips": 13139,
    "county_name": "Hall",
    "county_weights": "{\"13139\": 57.86, \"13187\": 37.19, \"13311\": 4.95}",
    "county_names_all": "Hall|Lumpkin|White",
    "county_fips_all": "13139|13187|13311",
    "imprecise": false,
    "military": false,
    "timezone": "America/New_York"
}