{
    "zip": 36043,
    "lat": 32.1939,
    "lng": -86.42811,
    "city": "Hope Hull",
    "state_id": "AL",
    "state_name": "Alabama",
    "zcta": true,
    "parent_zcta": NaN,
    "population": 3230.0,
    "density": 10.1,
    "county_fips": 1085,
    "county_name": "Lowndes",
    "county_weights": "{\"01085\": 55.77, \"01101\": 44.23}",
    "county_names_all": "Lowndes|Montgomery",
    "county_fips_all": "01085|01101",
    "imprecise": false,
    "military": false,
    "timezone": "America/Chicago"
}