{
    "zip": 47834,
    "lat": 39.52423,
    "lng": -87.12276,
    "city": "Brazil",
    "state_id": "IN",
    "state_name": "Indiana",
    "zcta": true,
    "parent_zcta": NaN,
    "population": 18773.0,
    "density": 47.0,
    "county_fips": 18021,
    "county_name": "Clay",
    "county_weights": "{\"18021\": 78.8, \"18121\": 12.13, \"18167\": 9.07}",
    "county_names_all": "Clay|Parke|Vigo",
    "county_fips_all": "18021|18121|18167",
    "imprecise": false,
    "military": false,
    "timezone": "America/Indiana/Indianapolis"
}