{
    "zip": 57544,
    "lat": 43.88374,
    "lng": -99.83647,
    "city": "Kennebec",
    "state_id": "SD",
    "state_name": "South Dakota",
    "zcta": true,
    "parent_zcta": NaN,
    "population": 461.0,
    "density": 0.7,
    "county_fips": 46085,
    "county_name": "Lyman",
    "county_weights": "{\"46085\": 93.88, \"46123\": 6.12}",
    "county_names_all": "Lyman|Tripp",
    "county_fips_all": "46085|46123",
    "imprecise": false,
    "military": false,
    "timezone": "America/Chicago"
}