{
    "zip": 58275,
    "lat": 47.68956,
    "lng": -97.10609,
    "city": "Reynolds",
    "state_id": "ND",
    "state_name": "North Dakota",
    "zcta": true,
    "parent_zcta": NaN,
    "population": 812.0,
    "density": 2.7,
    "county_fips": 38035,
    "county_name": "Grand Forks",
    "county_weights": "{\"38035\": 70.48, \"38097\": 29.52}",
    "county_names_all": "Grand Forks|Traill",
    "county_fips_all": "38035|38097",
    "imprecise": false,
    "military": false,
    "timezone": "America/Chicago"
}