{
    "zip": 65061,
    "lat": 38.59773,
    "lng": -91.638,
    "city": "Morrison",
    "state_id": "MO",
    "state_name": "Missouri",
    "zcta": true,
    "parent_zcta": NaN,
    "population": 620.0,
    "density": 4.5,
    "county_fips": 29073,
    "county_name": "Gasconade",
    "county_weights": "{\"29073\": 53.64, \"29151\": 46.36}",
    "county_names_all": "Gasconade|Osage",
    "county_fips_all": "29073|29151",
    "imprecise": false,
    "military": false,
    "timezone": "America/Chicago"
}