{
    "zip": 70444,
    "lat": 30.90833,
    "lng": -90.48707,
    "city": "Kentwood",
    "state_id": "LA",
    "state_name": "Louisiana",
    "zcta": true,
    "parent_zcta": NaN,
    "population": 9307.0,
    "density": 14.7,
    "county_fips": 22105,
    "county_name": "Tangipahoa",
    "county_weights": "{\"22105\": 71.37, \"22091\": 27.58, \"22117\": 1.05}",
    "county_names_all": "Tangipahoa|St. Helena|Washington",
    "county_fips_all": "22105|22091|22117",
    "imprecise": false,
    "military": false,
    "timezone": "America/Chicago"
}