{
    "zip": 77656,
    "lat": 30.42866,
    "lng": -94.16887,
    "city": "Silsbee",
    "state_id": "TX",
    "state_name": "Texas",
    "zcta": true,
    "parent_zcta": NaN,
    "population": 17132.0,
    "density": 37.7,
    "county_fips": 48199,
    "county_name": "Hardin",
    "county_weights": "{\"48199\": 86.35, \"48457\": 13.65}",
    "county_names_all": "Hardin|Tyler",
    "county_fips_all": "48199|48457",
    "imprecise": false,
    "military": false,
    "timezone": "America/Chicago"
}