{
    "zip": 79252,
    "lat": 34.31001,
    "lng": -99.80874,
    "city": "Quanah",
    "state_id": "TX",
    "state_name": "Texas",
    "zcta": true,
    "parent_zcta": NaN,
    "population": 2642.0,
    "density": 1.9,
    "county_fips": 48197,
    "county_name": "Hardeman",
    "county_weights": "{\"48197\": 96.77, \"48101\": 3.23}",
    "county_names_all": "Hardeman|Cottle",
    "county_fips_all": "48197|48101",
    "imprecise": false,
    "military": false,
    "timezone": "America/Chicago"
}