{
    "zip": 3602,
    "lat": 43.13751,
    "lng": -72.32938,
    "city": "Alstead",
    "state_id": "NH",
    "state_name": "New Hampshire",
    "zcta": true,
    "parent_zcta": NaN,
    "population": 2415.0,
    "density": 15.2,
    "county_fips": 33005,
    "county_name": "Cheshire",
    "county_weights": "{\"33005\": 63.49, \"33019\": 36.51}",
    "county_names_all": "Cheshire|Sullivan",
    "county_fips_all": "33005|33019",
    "imprecise": false,
    "military": false,
    "timezone": "America/New_York"
}