{
    "zip": 5056,
    "lat": 43.52895,
    "lng": -72.72397,
    "city": "Plymouth",
    "state_id": "VT",
    "state_name": "Vermont",
    "zcta": true,
    "parent_zcta": NaN,
    "population": 350.0,
    "density": 3.3,
    "county_fips": 50027,
    "county_name": "Windsor",
    "county_weights": "{\"50027\": 99.01, \"50021\": 0.99}",
    "county_names_all": "Windsor|Rutland",
    "county_fips_all": "50027|50021",
    "imprecise": false,
    "military": false,
    "timezone": "America/New_York"
}