{
    "zip": 45388,
    "lat": 40.32799,
    "lng": -84.47901,
    "city": "Yorkshire",
    "state_id": "OH",
    "state_name": "Ohio",
    "zcta": true,
    "parent_zcta": NaN,
    "population": 727.0,
    "density": 16.1,
    "county_fips": 39037,
    "county_name": "Darke",
    "county_weights": "{\"39037\": 95.79, \"39149\": 2.27, \"39107\": 1.94}",
    "county_names_all": "Darke|Shelby|Mercer",
    "county_fips_all": "39037|39149|39107",
    "imprecise": false,
    "military": false,
    "timezone": "America/New_York"
}