{
    "zip": 47201,
    "lat": 39.15074,
    "lng": -85.99432,
    "city": "Columbus",
    "state_id": "IN",
    "state_name": "Indiana",
    "zcta": true,
    "parent_zcta": NaN,
    "population": 48602.0,
    "density": 93.3,
    "county_fips": 18005,
    "county_name": "Bartholomew",
    "county_weights": "{\"18005\": 84.67, \"18013\": 15.33}",
    "county_names_all": "Bartholomew|Brown",
    "county_fips_all": "18005|18013",
    "imprecise": false,
    "military": false,
    "timezone": "America/Indiana/Indianapolis"
}