{
    "zip": 56678,
    "lat": 47.4298,
    "lng": -95.11768,
    "city": "Solway",
    "state_id": "MN",
    "state_name": "Minnesota",
    "zcta": true,
    "parent_zcta": NaN,
    "population": 1708.0,
    "density": 5.2,
    "county_fips": 27007,
    "county_name": "Beltrami",
    "county_weights": "{\"27007\": 52.43, \"27057\": 43.0, \"27029\": 4.57}",
    "county_names_all": "Beltrami|Hubbard|Clearwater",
    "county_fips_all": "27007|27057|27029",
    "imprecise": false,
    "military": false,
    "timezone": "America/Chicago"
}