{
    "zip": 71639,
    "lat": 33.89143,
    "lng": -91.54414,
    "city": "Dumas",
    "state_id": "AR",
    "state_name": "Arkansas",
    "zcta": true,
    "parent_zcta": NaN,
    "population": 5385.0,
    "density": 11.2,
    "county_fips": 5079,
    "county_name": "Lincoln",
    "county_weights": "{\"05079\": 52.26, \"05041\": 47.74}",
    "county_names_all": "Lincoln|Desha",
    "county_fips_all": "05079|05041",
    "imprecise": false,
    "military": false,
    "timezone": "America/Chicago"
}