{
    "zip": 78014,
    "lat": 28.39837,
    "lng": -99.10946,
    "city": "Cotulla",
    "state_id": "TX",
    "state_name": "Texas",
    "zcta": true,
    "parent_zcta": NaN,
    "population": 5542.0,
    "density": 2.4,
    "county_fips": 48283,
    "county_name": "La Salle",
    "county_weights": "{\"48283\": 97.68, \"48127\": 2.32}",
    "county_names_all": "La Salle|Dimmit",
    "county_fips_all": "48283|48127",
    "imprecise": false,
    "military": false,
    "timezone": "America/Chicago"
}