{
    "zip": 24128,
    "lat": 37.3426,
    "lng": -80.47196,
    "city": "Newport",
    "state_id": "VA",
    "state_name": "Virginia",
    "zcta": true,
    "parent_zcta": NaN,
    "population": 1660.0,
    "density": 8.7,
    "county_fips": 51071,
    "county_name": "Giles",
    "county_weights": "{\"51071\": 71.37, \"51045\": 28.63}",
    "county_names_all": "Giles|Craig",
    "county_fips_all": "51071|51045",
    "imprecise": false,
    "military": false,
    "timezone": "America/New_York"
}