{
    "zip": 46127,
    "lat": 39.71766,
    "lng": -85.3158,
    "city": "Falmouth",
    "state_id": "IN",
    "state_name": "Indiana",
    "zcta": true,
    "parent_zcta": NaN,
    "population": 431.0,
    "density": 8.1,
    "county_fips": 18139,
    "county_name": "Rush",
    "county_weights": "{\"18139\": 71.06, \"18041\": 28.94}",
    "county_names_all": "Rush|Fayette",
    "county_fips_all": "18139|18041",
    "imprecise": false,
    "military": false,
    "timezone": "America/Indiana/Indianapolis"
}