{
    "zip": 73764,
    "lat": 35.85738,
    "lng": -98.20307,
    "city": "Omega",
    "state_id": "OK",
    "state_name": "Oklahoma",
    "zcta": true,
    "parent_zcta": NaN,
    "population": 202.0,
    "density": 1.7,
    "county_fips": 40073,
    "county_name": "Kingfisher",
    "county_weights": "{\"40073\": 58.35, \"40011\": 41.65}",
    "county_names_all": "Kingfisher|Blaine",
    "county_fips_all": "40073|40011",
    "imprecise": false,
    "military": false,
    "timezone": "America/Chicago"
}