{
    "zip": 78933,
    "lat": 29.77209,
    "lng": -96.33829,
    "city": "Cat Spring",
    "state_id": "TX",
    "state_name": "Texas",
    "zcta": true,
    "parent_zcta": NaN,
    "population": 1211.0,
    "density": 3.6,
    "county_fips": 48089,
    "county_name": "Colorado",
    "county_weights": "{\"48089\": 69.32, \"48015\": 30.68}",
    "county_names_all": "Colorado|Austin",
    "county_fips_all": "48089|48015",
    "imprecise": false,
    "military": false,
    "timezone": "America/Chicago"
}